{
  "$schema": "https://developer.microsoft.com/json-schemas/fabric/item/report/definition/visualContainer/2.10.0/schema.json",
  "name": "5f646a3d9dbf62d33711",
  "position": {
    "x": 0,
    "y": 5,
    "z": 1000,
    "height": 113.75,
    "width": 225,
    "tabOrder": 22000
  },
  "visual": {
    "visualType": "textbox",
    "objects": {
      "general": [
        {
          "properties": {
            "paragraphs": [
              {
                "textRuns": [
                  {
                    "value": "Vendas Televendas",
                    "textStyle": {
                      "fontWeight": "bold",
                      "fontSize": "28pt",
                      "color": "#ffffff"
                    }
                  }
                ]
              }
            ]
          }
        }
      ]
    },
    "visualContainerObjects": {
      "background": [
        {
          "properties": {
            "show": {
              "expr": {
                "Literal": {
                  "Value": "false"
                }
              }
            }
          }
        }
      ]
    },
    "drillFilterOtherVisuals": true
  },
  "parentGroupName": "6faaa7d7bc3d15ef6c63"
}